vk_captcha/__init__.py
vk_captcha/__main__.py
vk_captcha/model.onnx
vk_captcha/solver.py
vk_captcha/vk_api_handler.py
vk_captcha-2.0.dist-info/METADATA
vk_captcha-2.0.dist-info/WHEEL
vk_captcha-2.0.dist-info/top_level.txt
vk_captcha-2.0.dist-info/RECORD
